tranquilo/__init__.py
tranquilo/_version.py
tranquilo/acceptance_decision.py
tranquilo/acceptance_sample_size.py
tranquilo/adjust_n_evals.py
tranquilo/adjust_radius.py
tranquilo/aggregate_models.py
tranquilo/bounds.py
tranquilo/clustering.py
tranquilo/config.py
tranquilo/estimate_variance.py
tranquilo/exploration_sample.py
tranquilo/filter_points.py
tranquilo/fit_models.py
tranquilo/geometry.py
tranquilo/get_component.py
tranquilo/handle_infinity.py
tranquilo/history.py
tranquilo/models.py
tranquilo/options.py
tranquilo/poisedness.py
tranquilo/process_arguments.py
tranquilo/region.py
tranquilo/rho_noise.py
tranquilo/sample_points.py
tranquilo/solve_subproblem.py
tranquilo/tranquilo.py
tranquilo/utilities.py
tranquilo/visualize.py
tranquilo/volume.py
tranquilo/weighting.py
tranquilo/wrap_criterion.py
tranquilo/subsolvers/_conjugate_gradient.py
tranquilo/subsolvers/_conjugate_gradient_fast.py
tranquilo/subsolvers/_steihaug_toint.py
tranquilo/subsolvers/_steihaug_toint_fast.py
tranquilo/subsolvers/_trsbox.py
tranquilo/subsolvers/_trsbox_fast.py
tranquilo/subsolvers/bntr.py
tranquilo/subsolvers/bntr_fast.py
tranquilo/subsolvers/fallback_subsolvers.py
tranquilo/subsolvers/gqtpar.py
tranquilo/subsolvers/gqtpar_fast.py
tranquilo/subsolvers/linear_subsolvers.py
tranquilo-0.0.5.dist-info/LICENSE
tranquilo-0.0.5.dist-info/METADATA
tranquilo-0.0.5.dist-info/WHEEL
tranquilo-0.0.5.dist-info/top_level.txt
tranquilo-0.0.5.dist-info/RECORD
