Metadata-Version: 2.1
Name: tranquilo
Version: 0.0.5
Summary: Trust-region optimizer for scalar, least-square and noisy problems
Home-page: https://github.com/OpenSourceEconomics/tranquilo
Author: Janos Gabler
Author-email: janos.gabler@gmail.com
License: MIT
Keywords: optimization,dfo,derivative free optimization,noisy optimization,parallel optimization,numerical optimization
Classifier: Development Status :: 3 - Alpha
Classifier: Intended Audience :: Science/Research
Classifier: License :: OSI Approved :: MIT License
Classifier: Operating System :: MacOS :: MacOS X
Classifier: Operating System :: Microsoft :: Windows
Classifier: Operating System :: POSIX
Classifier: Programming Language :: Python :: 3
Classifier: Programming Language :: Python :: 3 :: Only
Classifier: Topic :: Scientific/Engineering
Requires-Python: >=3.8
License-File: LICENSE
Requires-Dist: estimagic >=0.4.2
Requires-Dist: numba
Requires-Dist: numpy >=1.17.0
Requires-Dist: pandas
Requires-Dist: plotly
Requires-Dist: scipy >=1.2.1
